{"visible":"true","items":[{"type":"image","url":"01.jpg","md":"![picture](content\/02%20Bu%CC%88hnenraum\/Alles%20muss\/01.jpg)"},{"type":"image","url":"02.jpg","md":"![picture](content\/02%20Bu%CC%88hnenraum\/Alles%20muss\/02.jpg)"},{"type":"image","url":"03.jpg","md":"![picture](content\/02%20Bu%CC%88hnenraum\/Alles%20muss\/03.jpg)"},{"type":"image","url":"04.jpg","md":"![picture](content\/02%20Bu%CC%88hnenraum\/Alles%20muss\/04.jpg)"},{"type":"text","url":"description.txt","md":"Titel Alles muss weg\n\nAlles muss weg!\n9 Tage urbaner Ausverkauf\nBegehbare Stadtinstallation im Schiffbau Z\u00fcrich 2011\/12\n\nKonzept Lukas B\u00e4rfuss, Katja Hagedorn, Anja Kerschkewicz, Bettina Meyer, Nadia Schrader\nTechnische Einrichtung Dani L\u00f6 tscher \/ Produktionsleitung Nadia Schrader \/ Beleuchtung\nMichel Gu\u0308ntert \/ Ton und Video Paul Hug, Markus Keller, Renata Vonarburg,\nHolger Wendt \/ Requisite Rock Battaglia, Marianne Boos, Seraina Heinz, Catia Koller, Dani L\u00e4uchli\n\n"}]}